{"stats":{"minecraft:killed_by":{"minecraft:player":2},"minecraft:mined":{"minecraft:diamond_ore":2,"minecraft:crafting_table":1,"minecraft:torch":1,"minecraft:granite":2,"minecraft:grass_block":1,"minecraft:diorite":38,"minecraft:wall_torch":4,"minecraft:redstone_ore":18,"minecraft:furnace":1,"minecraft:birch_log":12,"minecraft:iron_ore":7,"minecraft:andesite":14,"minecraft:birch_leaves":1,"minecraft:oak_log":8,"minecraft:coal_ore":4,"minecraft:gravel":36,"minecraft:dirt":98,"minecraft:stone":242,"minecraft:gold_ore":5,"minecraft:infested_stone":4},"minecraft:crafted":{"minecraft:cooked_beef":3,"minecraft:wooden_sword":1,"minecraft:oak_slab":6,"minecraft:oak_planks":32,"minecraft:stone_shovel":1,"minecraft:crafting_table":2,"minecraft:wooden_pickaxe":1,"minecraft:iron_helmet":1,"minecraft:furnace":2,"minecraft:bucket":1,"minecraft:stone_axe":2,"minecraft:ladder":48,"minecraft:stick":128,"minecraft:iron_ingot":15,"minecraft:iron_pickaxe":1,"minecraft:stone_pickaxe":1,"minecraft:iron_leggings":1,"minecraft:chest":1,"minecraft:gold_ingot":5,"minecraft:stone_hoe":1},"minecraft:killed":{"minecraft:zombie":1,"minecraft:silverfish":4,"minecraft:cow":2},"minecraft:picked_up":{"minecraft:birch_log":12,"minecraft:crafting_table":1,"minecraft:andesite":32,"minecraft:birch_planks":32,"minecraft:flint":10,"minecraft:oak_log":8,"minecraft:lapis_lazuli":2,"minecraft:dirt":112,"minecraft:bone":2,"minecraft:beef":3,"minecraft:iron_ore":6,"minecraft:oak_planks":11,"minecraft:furnace":1,"minecraft:torch":29,"minecraft:gravel":26,"minecraft:diorite":31,"minecraft:gold_ore":5,"minecraft:redstone":79,"minecraft:rotten_flesh":2,"minecraft:diamond":1,"minecraft:granite":2,"minecraft:coal":11,"minecraft:cobblestone":229},"minecraft:broken":{"minecraft:stone_pickaxe":1,"minecraft:wooden_pickaxe":1},"minecraft:dropped":{"minecraft:dirt":1,"minecraft:andesite":18},"minecraft:used":{"minecraft:water_bucket":1,"minecraft:birch_planks":1,"minecraft:stone_shovel":27,"minecraft:stone_pickaxe":131,"minecraft:ladder":41,"minecraft:chest":1,"minecraft:wooden_pickaxe":59,"minecraft:cooked_chicken":3,"minecraft:torch":15,"minecraft:dirt":62,"minecraft:oak_slab":4,"minecraft:crafting_table":3,"minecraft:oak_stairs":1,"minecraft:iron_pickaxe":172,"minecraft:stone_axe":22,"minecraft:wooden_sword":20,"minecraft:furnace":3,"minecraft:bucket":1,"minecraft:andesite":12,"minecraft:cooked_beef":3},"minecraft:custom":{"minecraft:interact_with_furnace":35,"minecraft:mob_kills":7,"minecraft:interact_with_crafting_table":26,"minecraft:play_one_minute":139602,"minecraft:leave_game":36,"minecraft:time_since_death":118407,"minecraft:climb_one_cm":29382,"minecraft:time_since_rest":120037,"minecraft:sprint_one_cm":74753,"minecraft:damage_taken":1131,"minecraft:walk_one_cm":268166,"minecraft:drop":14,"minecraft:damage_dealt":1160,"minecraft:fly_one_cm":14281,"minecraft:open_chest":9,"minecraft:crouch_one_cm":366,"minecraft:deaths":2,"minecraft:sneak_time":75,"minecraft:walk_under_water_one_cm":5664,"minecraft:jump":428,"minecraft:walk_on_water_one_cm":6342,"minecraft:fall_one_cm":2947}},"DataVersion":2584}